{
  "абажур": "lampshade",
  "абака": "abaca",
  "аббат": "abbot",
  "аббатиса": "abbess",
  "аббатство": "abbey",
  "аббревиатура": "abbreviation",
  "абдикация": "abdication",
  "абдоминальный": "abdominal",
  "аберрация": "aberration",
  "абиссальный": "abyssal",
  "абиогенез": "abiogenesis",
  "абиотический": "abiotic",
  "абляция": "ablation",
  "аболиционизм": "abolitionism",
  "аболиционист": "abolitionist",
  "абонент": "subscriber",
  "абонентская плата": "subscription fee",
  "абонемент": "season ticket",
  "абориген": "aborigine",
  "абордаж": "boarding (of a ship)",
  "аборт": "abortion",
  "абразив": "abrasive",
  "абразия": "abrasion",
  "абрикос": "apricot",
  "абрис": "outline",
  "абсент": "absinthe",
  "абсолютизм": "absolutism",
  "абсорбент": "absorbent",
  "абстрагироваться": "to abstract oneself",
  "абстракционизм": "abstractionism",
  "абстракционист": "abstractionist",
  "авангард": "avant-garde",
  "авангардизм": "avant-gardism",
  "авангардист": "avant-gardist",
  "аванпост": "outpost",
  "авиабаза": "airbase",
  "авиабилет": "plane ticket",
  "авианосец": "aircraft carrier",
  "авиапочта": "airmail",
  "автовокзал": "bus station",
  "автозаправка": "gas station",
  "автокефалия": "autocephaly",
  "автоколонна": "motorcade",
  "автоматизировать": "to automate",
  "автомобилестроение": "automotive industry",
  "автомобильный": "automotive",
  "авторучка": "pen",
  "агава": "agave",
  "агат": "agate",
  "агностик": "agnostic",
  "агностицизм": "agnosticism",
  "адаптировать": "to adapt",
  "адыгеец": "Adyghe (male)",
  "адыгейка": "Adyghe (female)",
  "адыгейский": "Adyghe (adj.)",
  "азотный": "nitrogenous",
  "аир": "calamus",
  "айва": "quince",
  "акация": "acacia",
  "аккомпаниатор": "accompanist",
  "акмеизм": "acmeism",
  "акмеист": "acmeist",
  "акне": "acne",
  "акционерное общество": "joint-stock company",
  "актёр": "actor",
  "алабай": "Alabai (Central Asian Shepherd Dog)",
  "алалия": "alalia",
  "албанец": "Albanian (male)",
  "албанка": "Albanian (female)",
  "албанский": "Albanian (adj.)",
  "алгебра": "algebra",
  "аллопатия": "allopathy",
  "алтаец": "Altai (male)",
  "алтайка": "Altai (female)",
  "алтайский": "Altai (adj.)",
  "альвеола": "alveolus",
  "амбулатория": "outpatient clinic",
  "амвон": "ambo",
  "американка": "American (female)",
  "аметист": "amethyst",
  "аммиак": "ammonia",
  "ампер": "ampere",
  "амфора": "amphora",
  "англичанка": "Englishwoman",
  "антарктический": "Antarctic",
  "анчоус": "anchovy",
  "аорта": "aorta",
  "апатия": "apathy",
  "апоплексия": "apoplexy",
  "аппендицит": "appendicitis",
  "арабский": "Arabic",
  "аргамак": "Argamak (horse breed)",
  "аргентинец": "Argentinian (male)",
  "аргентинка": "Argentinian (female)",
  "аргентинский": "Argentinian (adj.)",
  "аркада": "arcade",
  "арктический": "Arctic",
  "артачиться": "to balk",
  "архар": "argali (mountain sheep)",
  "атлетика": "athletics",
  "африканец": "African (male)",
  "африканка": "African (female)",
  "ахроматический": "achromatic",
  "ацетон": "acetone",
  "аэробика": "aerobics",
  "аэродинамика": "aerodynamics",
  "аэрофотосъёмка": "aerial photography",
  "аэрошина": "aerotire",
  "а": "and",
  "а вдруг": "what if",
  "а ведь": "indeed",
  "а воз и ныне там": "and the cart is still there",
  "а вот": "but here",
  "а если": "and if",
  "а еще": "and also",
  "а затем": "and then",
  "а значит": "and therefore",
  "а именно": "namely",
  "а как же": "and what about",
  "а не": "and not",
  "а также": "as well as",
  "а то": "otherwise",
  "а точнее": "more precisely",
  "а это значит": "and this means",
  "абзац": "paragraph",
  "абсолют": "absolute",
  "абсолютно": "absolutely",
  "абсолютно точно": "absolutely certain",
  "абсолютность": "absoluteness",
  "абсолютный": "absolute",
  "абсорбция": "absorption",
  "абстиненция": "abstinence",
  "абстрагирование": "abstraction",
  "абстрагированность": "abstractedness",
  "абстракт": "abstract",
  "абстрактно": "abstractly",
  "абстрактность": "abstractness",
  "абстрактный": "abstract",
  "абстракция": "abstraction",
  "абсурд": "absurd",
  "абсурдно": "absurdly",
  "абсурдность": "absurdity",
  "абсурдный": "absurd",
  "абсцесс": "abscess",
  "абы как": "anyhow",
  "абьюз": "abuse",
  "абьюзер": "abuser",
  "аварийная ситуация": "emergency situation",
  "аварийный": "emergency",
  "авария": "accident",
  "аванс": "advance",
  "авансцена": "proscenium",
  "авантаж": "advantage",
  "авантажно": "advantageously",
  "авантажный": "advantageous",
  "авантюра": "venture",
  "авантюризм": "adventurism",
  "авантюрист": "adventurer",
  "авантюристка": "adventuress",
  "авантюрный": "adventurous",
  "аватар": "avatar",
  "аватарка": "profile picture",
  "авеню": "avenue",
  "авераж": "average",
  "аверс": "obverse",
  "авиакомпания": "airline",
  "авиалиния": "airline",
  "авиатор": "aviator",
  "авиация": "aviation",
  "авизо": "advice",
  "авитаминоз": "avitaminosis",
  "авось": "perhaps",
  "авоська": "string bag",
  "аврал": "rush job",
  "авральный": "urgent",
  "аврора": "aurora",
  "август": "august",
  "австралия": "Australia",
  "автаркия": "autarky",
  "авто": "car",
  "автобан": "autobahn",
  "автобиография": "autobiography",
  "автобус": "bus",
  "автовладелец": "car owner",
  "автограф": "autograph",
  "автодидакт": "autodidact",
  "автодорога": "highway",
  "автозапчасти": "car parts",
  "автократия": "autocracy",
  "автолюбитель": "car enthusiast",
  "автомат": "machine",
  "автоматизация": "automation",
  "автоматизирование": "automatization",
  "автоматизированный": "automated",
  "автоматизм": "automatism",
  "автоматика": "automation",
  "автоматически": "automatically",
  "автоматический": "automatic",
  "автомашина": "automobile",
  "автомобиль": "car",
  "автомобилист": "motorist",
  "автомойка": "car wash",
  "автономизация": "autonomization",
  "автономия": "autonomy",
  "автономно": "autonomously",
  "автономность": "autonomy",
  "автономный": "autonomous",
  "автопарк": "car fleet",
  "автопортрет": "self-portrait",
  "автор": "author",
  "авторизация": "authorization",
  "авторизованный": "authorized",
  "авторитаризм": "authoritarianism",
  "авторитарность": "authoritarian nature",
  "авторитарный": "authoritarian",
  "авторитет": "authority",
  "авторитетно": "authoritatively",
  "авторитетность": "credibility",
  "авторитетный": "authoritative",
  "авторский": "author's",
  "авторство": "authorship",
  "авторы": "authors",
  "автосалон": "car dealership",
  "автосервис": "car service",
  "автострада": "freeway",
  "автотранспорт": "motor transport",
  "автофелляция": "autofellatio",
  "автофилия": "autophilia",
  "автохтон": "autochthon",
  "автохтонный": "autochthonous",
  "автошкола": "driving school",
  "авуары": "assets",
  "ага": "aha",
  "агапа": "agape (love)",
  "агапэ": "agape (love)",
  "агенда": "agenda",
  "агенство": "agency",
  "агент": "agent",
  "агентство": "agency",
  "агирлик": "no direct translation (Turkish loanword, weight)",
  "агитатор": "agitator",
  "агитация": "agitation",
  "агитировать": "agitate",
  "агломерация": "agglomeration",
  "агнец": "lamb",
  "агнозия": "agnosia",
  "агония": "agony",
  "агорафобия": "agoraphobia",
  "аграмант": "no direct translation (ornament)",
  "аграрий": "agrarian",
  "аграрный": "agrarian",
  "агрегасьон": "aggregation",
  "агрегат": "unit",
  "агрегатный": "aggregate",
  "агрегатор": "aggregator",
  "агрегация": "aggregation",
  "агрегирование": "aggregation",
  "агрегированный": "aggregated",
  "агрессивно": "aggressively",
  "агрессивность": "aggressiveness",
  "агрессивный": "aggressive",
  "агрессия": "aggression",
  "агрессор": "aggressor",
  "агроном": "agronomist",
  "агрономия": "agronomy",
  "адажио": "adagio",
  "адам": "Adam ",
  "адамант": "adamant",
  "адаптационный": "adaptive",
  "адаптация": "adaptation",
  "адаптер": "adapter",
  "адаптивность": "adaptivity",
  "адаптивный": "adaptive",
  "адаптирование": "adapting",
  "адаптированность": "adaptedness",
  "адаптированный": "adapted",
  "адвайзер": "adviser",
  "адверсэр": "adversary",
  "адвокат": "lawyer",
  "адгезия": "adhesion",
  "аддикция": "addiction",
  "аддитивность": "additivity",
  "аддитивный": "additive",
  "адекват": "adequate",
  "адекватно": "adequately",
  "адекватность": "adequacy",
  "адекватный": "adequate",
  "адепт": "adept",
  "админ": "admin",
  "админ-панель": "admin-panel",
  "административный": "administrative",
  "администратор": "administrator",
  "администрация": "administration",
  "администрирование": "administration",
  "администрировать": "administer",
  "адмирал": "admiral",
  "адмирация": "admiration",
  "адорант": "adorant",
  "адреналин": "adrenaline",
  "адрес": "address",
  "адреса": "addresses",
  "адресант": "sender",
  "адресат": "recipient",
  "адресно": "addressed",
  "адресность": "addressability",
  "адресный": "addressed",
  "адресованный": "addressed",
  "адресовать": "address",
  "адский": "hellish",
  "адсорбция": "adsorption",
  "адъютант": "adjutant",
  "адью": "adieu",
  "адюльтер": "adultery",
  "ажиотаж": "hype",
  "ажитация": "agitation",
  "ажно": "even ",
  "ажур": "openwork",
  "ажурный": "openwork",
  "азарт": "excitement",
  "азартно": "excitedly",
  "азартность": "excitement",
  "азартные игры": "gambling",
  "азартный": "exciting",
  "азбука": "alphabet",
  "азбуковник": "primer",
  "азельготрипсия": "no direct translation (medical term)",
  "азиат": "Asian",
  "азиатский": "asian",
  "азимут": "azimuth",
  "азия": "Asia",
  "азы": "basics",
  "аид": "Hades ",
  "аист": "stork",
  "айда": "come on",
  "айдан": "Aidan ",
  "айдентика": "branding",
  "айдын": "no direct translation (proper name or term)",
  "аймак": "no direct translation (regional term)",
  "айс": "ice",
  "айсберг": "iceberg",
  "айти": "IT",
  "айтишник": "IT specialist",
  "айфон": "iPhone",
  "академик": "academician",
  "академический": "academic",
  "академия": "academy",
  "аква": "aqua",
  "акваланг": "aqualung",
  "аквалангист": "scuba diver",
  "аквамарин": "aquamarine",
  "акварель": "watercolor",
  "аквариум": "aquarium",
  "акватория": "water area",
  "аки": "as if ",
  "аким": "Akim ",
  "акка": "acca",
  "аккаунт": "account",
  "акклиматизация": "acclimatization",
  "аккомодация": "accommodation",
  "аккомпанемент": "accompaniment",
  "аккорд": "chord",
  "аккредитация": "accreditation",
  "аккредитив": "letter of credit",
  "аккредитованный": "accredited",
  "аккультурация": "acculturation",
  "аккумулирование": "accumulation",
  "аккумулированный": "accumulated",
  "аккумулятор": "battery",
  "аккумуляция": "accumulation",
  "аккурат": "careful",
  "аккурат-де": "exactly",
  "аккуратист": "perfectionist",
  "аккуратнее": "more careful",
  "аккуратно": "carefully",
  "аккуратность": "carefulness",
  "аккуратный": "neat",
  "акме": "acme",
  "акно": "acne",
  "акробат": "acrobat",
  "акробатика": "acrobatics",
  "акроним": "acronym",
  "акрополь": "acropolis",
  "аксакал": "elder",
  "акселерат": "accelerated youth",
  "акселератор": "accelerator",
  "акселерация": "acceleration",
  "аксессуар": "accessory",
  "аксиологический": "axiological",
  "аксиология": "axiology",
  "аксиома": "axiom",
  "акстись": "shame on you ",
  "актант": "actant",
  "акт": "act",
  "актер": "actor",
  "актер театра": "theater actor",
  "актерство": "acting",
  "актив": "asset",
  "активация": "activation",
  "активизация": "activation",
  "активизировать": "activate",
  "активизироваться": "become active",
  "активизируется": "is activated",
  "активист": "activist",
  "активистка": "female activist",
  "активная жизненная позиция": "active life stance",
  "активная работа": "active work",
  "активное участие": "active participation",
  "активно": "actively",
  "активность": "activity",
  "активный": "active",
  "активный отдых": "active recreation",
  "активы": "assets",
  "актор": "actor",
  "актриса": "actress",
  "актуализация": "actualization",
  "актуализирование": "actualizing",
  "актуализированный": "actualized",
  "актуальная проблема": "pressing issue",
  "актуально": "currently",
  "актуальность": "relevance",
  "актуальный": "actual",
  "акула": "shark",
  "акула пера": "shark of the pen",
  "акустика": "acoustics",
  "акустический": "acoustic",
  "акцент": "emphasis",
  "акцентировать": "emphasize",
  "акцентировать внимание": "focus attention",
  "акцентирование": "accentuation",
  "акцентируя": "emphasizing",
  "акцентный": "accented",
  "акцентуация": "accentuation",
  "акцепт": "acceptance",
  "акциз": "excise",
  "акционер": "shareholder",
  "акции": "promotions",
  "акция": "share",
  "акын": "bard",
  "ала": "no direct translation (exclamation)",
  "алапажный": "no direct translation (related to payment)",
  "алармист": "alarmist",
  "алгоритм": "algorithm",
  "алгоритмизация": "algorithmization",
  "але": "hello (informal)",
  "александр": "Alexander ",
  "алексей": "Alexey ",
  "алена": "Alena ",
  "алентовый": "no direct translation (rare term)",
  "алиби": "alibi",
  "алименты": "alimony",
  "алина": "Alina ",
  "алиса": "Alice ",
  "алкаш": "drunkard",
  "алкашка": "female drunkard",
  "алкоголизм": "alcoholism",
  "алкоголик": "alcoholic",
  "алкоголичка": "female alcoholic",
  "алкоголь": "alcohol",
  "алкогольный": "alcoholic",
  "аллах": "Allah ",
  "аллегорический": "allegorical",
  "аллегория": "allegory",
  "аллелопатия": "allelopathy",
  "аллерген": "allergen",
  "аллергия": "allergy",
  "аллея": "alley",
  "аллигатор": "alligator",
  "аллилуйя": "hallelujah",
  "аллитерация": "alliteration",
  "алло": "hello (phone greeting)",
  "аллокация": "allocation",
  "аллюзия": "allusion",
  "аллюр": "gait",
  "алмаз": "diamond",
  "алмазный": "diamond",
  "алогизм": "illogicality",
  "алогичный": "illogical",
  "алоэ": "aloe",
  "алый": "scarlet",
  "алтарь": "altar",
  "алтын": "altyn ",
  "алюминий": "aluminum",
  "алфавит": "alphabet",
  "алхимик": "alchemist",
  "алхимия": "alchemy",
  "алчность": "greed",
  "алчный": "greedy",
  "алчущий": "craving",
  "альбедо": "albedo",
  "альбинос": "albino",
  "альбом": "album",
  "альвар": "no direct translation (architectural term)",
  "альковный": "alcove",
  "альма-матер": "alma mater",
  "альманах": "almanac",
  "альпинист": "climber",
  "альтерация": "alteration",
  "альтернат": "alternative",
  "альтернатива": "alternative",
  "альтернативно": "alternatively",
  "альтернативно одаренный": "alternatively gifted",
  "альтернативность": "alternativeness",
  "альтернативный": "alternative",
  "альтруизм": "altruism",
  "альтруист": "altruist",
  "альтруистический": "altruistic",
  "альтруистичный": "altruistic",
  "альфа": "alpha",
  "альфа и омега": "alpha and omega",
  "альфа-самец": "alpha male",
  "альфонс": "gigolo",
  "альянс": "alliance",
  "амазонка": "Amazon",
  "амальгама": "amalgam",
  "аматор": "amateur",
  "амба": "no direct translation (exclamation)",
  "амбал": "big guy",
  "амбар": "barn",
  "амбассадор": "ambassador",
  "амбивалентно": "ambivalently",
  "амбивалентность": "ambivalence",
  "амбивалентный": "ambivalent",
  "амбиент": "ambient",
  "амбиции": "ambitions",
  "амбициозно": "ambitiously",
  "амбициозность": "ambitiousness",
  "амбициозный": "ambitious",
  "амбиция": "ambition",
  "амбразура": "embrasure",
  "амбре": "ambiance",
  "амброзия": "ambrosia",
  "амбьянс": "ambiance",
  "амеба": "amoeba",
  "америка": "America",
  "американец": "American",
  "американский": "American",
  "амиго": "amigo",
  "амикошонство": "familiarity",
  "аминь": "amen",
  "амнезия": "amnesia",
  "амнистия": "amnesty",
  "аморал": "amoral",
  "аморально": "amorally",
  "аморальность": "amorality",
  "аморальный": "amoral",
  "амортизатор": "shock absorber",
  "амортизация": "amortization",
  "аморфность": "amorphousness",
  "аморфный": "amorphous",
  "амплитуда": "amplitude",
  "амплификация": "amplification",
  "амплуа": "role",
  "ампула": "ampoule",
  "ампутация": "amputation",
  "амулет": "amulet",
  "амуниция": "ammunition",
  "амур": "Cupid",
  "амурные дела": "love affairs",
  "амурный": "amorous",
  "амуры": "love affairs",
  "амфетамин": "amphetamine",
  "амфибия": "amphibian",
  "амфитеатр": "amphitheater",
  "амфитрион": "host",
  "анагенез": "anagenesis",
  "анагогия": "anagogy",
  "анаграмма": "anagram",
  "анализ": "analysis",
  "анализатор": "analyzer",
  "анализирование": "analyzing",
  "анализировать": "analyze",
  "анализируемый": "analyzed",
  "аналитик": "analyst",
  "аналитика": "analytics",
  "аналитически": "analytically",
  "аналитический": "analytical",
  "аналитичность": "analyticity",
  "аналог": "analog",
  "аналогичная": "analogous",
  "аналогично": "analogously",
  "аналогичного": "analogous",
  "аналогичное": "analogous",
  "аналогичной": "analogous",
  "аналогичность": "analogousness",
  "аналогичную": "analogous",
  "аналогичные": "analogous",
  "аналогичный": "analogous",
  "аналогичным": "analogous",
  "аналогичными": "analogous",
  "аналогичных": "analogous",
  "аналогия": "analogy",
  "аналоговый": "analog",
  "анамнез": "anamnesis",
  "ананас": "pineapple",
  "ананке": "Ananke",
  "анархизм": "anarchism",
  "анархист": "anarchist",
  "анархия": "anarchy",
  "анастасия": "Anastasia ",
  "анатомический": "anatomical",
  "анатомия": "anatomy",
  "анафема": "anathema",
  "анафемский": "anathema-like",
  "анафора": "anaphora",
  "анахорет": "anchorite",
  "анахронизм": "anachronism",
  "анахроничный": "anachronistic",
  "анаша": "hashish",
  "ангажемент": "engagement",
  "ангажированность": "bias",
  "ангажированный": "biased",
  "ангар": "hangar",
  "ангел": "angel",
  "ангел-хранитель": "guardian angel",
  "ангельский": "angelic",
  "ангельский голосок": "angelic voice",
  "ангина": "tonsillitis",
  "английский": "English",
  "англичанин": "Englishman",
  "англия": "England",
  "андеграунд": "underground",
  "андрей": "Andrey",
  "андроид": "android",
  "анекдот": "joke",
  "анемия": "anemia",
  "анестезия": "anesthesia",
  "аниматор": "animator",
  "анимация": "animation",
  "аниме": "anime",
  "анкета": "questionnaire",
  "анкетирование": "surveying",
  "анклав": "enclave",
  "анкор": "anchor",
  "анна": "Anna ",
  "анналы": "annals",
  "аннексия": "annexation",
  "аннигиляция": "annihilation",
  "аннотация": "annotation",
  "аннулирование": "annulment",
  "аномалия": "anomaly",
  "аномально": "anomalously",
  "аномальный": "anomalous",
  "аномия": "anomie",
  "аноним": "anonymous person",
  "анонимно": "anonymously",
  "анонимность": "anonymity",
  "анонимный": "anonymous",
  "анонс": "announcement",
  "анонсировать": "announce",
  "анорексия": "anorexia",
  "ансамбль": "ensemble",
  "антагонизм": "antagonism",
  "антагонист": "antagonist",
  "антагонистический": "antagonistic",
  "антагонистичность": "antagonism",
  "антарктида": "Antarctica",
  "антенна": "aerial",
  "анти": "anti",
  "антибактериальный": "antibacterial",
  "антибиотик": "antibiotic",
  "антивирус": "antivirus",
  "антигерой": "antihero",
  "антигуманный": "inhumane",
  "антидепрессант": "antidepressant",
  "антидот": "antidote",
  "антик": "antique",
  "антиквар": "antiquarian",
  "антиквариат": "antiques",
  "антикварный": "antique",
  "антикризисный": "anti-crisis",
  "антимония": "antimony",
  "антиморальный": "amoral",
  "антиномия": "antinomy",
  "антиобщественный": "antisocial",
  "антиоксидант": "antioxidant",
  "антипатия": "antipathy",
  "антипод": "antipode",
  "антипример": "counterexample",
  "антиреклама": "negative advertising",
  "антисанитария": "unsanitary conditions",
  "антисемит": "antisemite",
  "антисемитизм": "antisemitism",
  "антисептик": "antiseptic",
  "антисептический": "antiseptic",
  "антисоциальный": "antisocial",
  "антистресс": "anti-stress",
  "антитеза": "antithesis",
  "антитетичность": "antithetical nature",
  "антиутопия": "dystopia",
  "антихрист": "Antichrist",
  "антиципация": "anticipation",
  "античность": "antiquity",
  "античный": "ancient",
  "антология": "anthology",
  "антон": "Anton ",
  "антоним": "antonym",
  "антракт": "intermission",
  "антрепренер": "impresario",
  "антресоль": "mezzanine",
  "антропогенный": "anthropogenic",
  "антропологический": "anthropological",
  "антропология": "anthropology",
  "антропоморфизм": "anthropomorphism",
  "антропоморфный": "anthropomorphic",
  "антропоцентризм": "anthropocentrism",
  "антропоцентрический": "anthropocentric",
  "антураж": "entourage",
  "антуражный": "scenic",
  "анфас": "full face",
  "анфилада": "enfilade",
  "аншлаг": "sold out",
  "аня": "Anya",
  "апгрейд": "upgrade",
  "апдейт": "update",
  "апеллировать": "appeal",
  "апелляция": "appeal",
  "апельсин": "orange",
  "апельсиновый": "orange",
  "аперитив": "aperitif",
  "апирия": "no direct translation (possible typo)",
  "аплодисменты": "applause",
  "аплодировать": "applaud",
  "апломб": "aplomb",
  "апогей": "apogee",
  "аподиктический": "apodictic",
  "апокалипсис": "apocalypse",
  "апокалиптический": "apocalyptic",
  "апокриф": "apocrypha",
  "апокрифический": "apocryphal",
  "аполитичность": "apolitical nature",
  "аполитичный": "apolitical",
  "аполлон": "Apollo ",
  "апологет": "apologist",
  "апологетика": "apologetics",
  "апология": "apology",
  "апория": "aporia",
  "апостериори": "a posteriori",
  "апостол": "apostle",
  "апостроф": "apostrophe",
  "апофегма": "apophthegm",
  "апофеоз": "apotheosis",
  "аппарат": "apparatus",
  "аппаратные средства": "hardware",
  "аппаратура": "equipment",
  "апартаменты": "suite",
  "апперцепция": "apperception",
  "аппетит": "appetite",
  "аппетитно": "appetizingly",
  "аппетитный": "appetizing",
  "аппликация": "application",
  "аппроксимация": "approximation",
  "апрель": "april",
  "априори": "a priori",
  "априорно": "a priori",
  "априорный": "a priori",
  "апробация": "approbation",
  "апробирование": "testing",
  "апробированный": "tested",
  "апроприация": "appropriation",
  "аптека": "pharmacy",
  "аптекарь": "pharmacist",
  "аптечка": "first-aid kit",
  "аптренд": "uptrend",
  "араб": "Arab",
  "арабески": "arabesques",
  "арахис": "peanut",
  "аранжировка": "arrangement",
  "арбалет": "crossbow",
  "арбитр": "arbiter",
  "арбитраж": "arbitration",
  "арбуз": "watermelon",
  "арго": "Argo ",
  "аргумент": "argument",
  "аргументация": "argumentation",
  "аргументированно": "reasonably",
  "аргументированный": "reasoned",
  "аргументировать": "argue",
  "аргументы": "arguments",
  "аргус": "Argus ",
  "ареал": "area",
  "арена": "arena",
  "аренда": "rent",
  "арендодатель": "landlord",
  "арендатор": "tenant",
  "арендовать": "rent",
  "арест": "arrest",
  "арестант": "prisoner",
  "арестовать": "arrest",
  "арете": "virtue",
  "аристократ": "aristocrat",
  "аристократизм": "aristocratism",
  "аристократический": "aristocratic",
  "аристократичность": "aristocratic nature",
  "аристократичный": "aristocratic",
  "аристократия": "aristocracy",
  "аристократка": "aristocrat (female)",
  "аритмия": "arrhythmia",
  "арифметика": "arithmetic",
  "ария": "aria",
  "арка": "arch",
  "аркан": "lasso",
  "арканум": "arcanum",
  "арктика": "Arctic",
  "арлекин": "harlequin",
  "армагеддон": "Armageddon",
  "армада": "armada",
  "арматура": "fittings",
  "армида": "Armida",
  "армирование": "reinforcement",
  "армия": "army",
  "армянин": "Armenian",
  "аромат": "aroma",
  "ароматизатор": "flavoring",
  "ароматный": "aromatic",
  "арсенал": "arsenal",
  "арт": "art",
  "арт-объект": "art object",
  "артель": "cooperative",
  "артем": "Artem",
  "артерия": "artery",
  "артефакт": "artifact",
  "артикул": "article",
  "артикуляция": "articulation",
  "артиллерия": "artillery",
  "артист": "artist",
  "артистизм": "artistry",
  "артистический": "artistic",
  "артистично": "artistically",
  "артистичность": "artistic nature",
  "артистичный": "artistic",
  "артистка": "actress",
  "артхаус": "arthouse",
  "арфа": "harp",
  "архаизм": "archaism",
  "архаика": "archaica",
  "архаический": "archaic",
  "архаичность": "archaic nature",
  "архаичный": "archaic",
  "архангел": "archangel",
  "архаровец": "rowdy",
  "археолог": "archaeologist",
  "археология": "archaeology",
  "архетип": "archetype",
  "архетипический": "archetypal",
  "архетипичный": "archetypal",
  "архив": "archive",
  "архиважный": "crucial",
  "архивариус": "archivist",
  "архивировано": "archived",
  "архивный": "archival",
  "архипелаг": "archipelago",
  "архитектоника": "architectonics",
  "архитектор": "architect",
  "архитектура": "architecture",
  "архитектурный": "architectural",
  "аршин": "arshin",
  "арык": "irrigation ditch",
  "арьергард": "rearguard",
  "асексуальность": "asexuality",
  "асимметричность": "asymmetry",
  "асимметричный": "asymmetric",
  "асимметрия": "asymmetry",
  "аскеза": "asceticism",
  "аскет": "ascetic",
  "аскетизм": "asceticism",
  "аскетический": "ascetic",
  "аскетично": "ascetically",
  "аскетичность": "ascetic nature",
  "аскетичный": "ascetic",
  "асоциальность": "asociality",
  "асоциальный": "asocial",
  "аспект": "aspect",
  "аспекты жизни": "aspects of life",
  "аспид": "viper",
  "аспирант": "graduate student",
  "аспирация": "aspiration",
  "аспирин": "aspirin",
  "асс": "ace",
  "ассамблея": "assembly",
  "ассасин": "assassin",
  "ассенизатор": "sewage worker",
  "ассигнация": "assignation",
  "ассигнование": "appropriation",
  "ассигнования": "appropriations",
  "ассимиляция": "assimilation",
  "ассистент": "assistant",
  "ассонанс": "assonance",
  "ассорти": "assortment",
  "ассортимент": "range",
  "ассоциативный": "associative",
  "ассоциация": "association",
  "ассоциирование": "association",
  "ассоциированный": "associated",
  "астана": "Astana ",
  "астения": "asthenia",
  "астероид": "asteroid",
  "астра": "aster",
  "астрал": "astral",
  "астральный": "astral",
  "астролог": "astrologer",
  "астрология": "astrology",
  "астронавт": "astronaut",
  "астроном": "astronomer",
  "астрономия": "astronomy",
  "асфальт": "asphalt",
  "асфиксия": "asphyxia",
  "ата": "no direct translation (exclamation)",
  "атавизм": "atavism",
  "атака": "attack",
  "атакующий": "attacker",
  "атаман": "ataman",
  "атас": "watch out",
  "атеизм": "atheism",
  "атеист": "atheist",
  "ателье": "studio",
  "атипичный": "atypical",
  "атлант": "Atlas ",
  "атлас": "atlas",
  "атлет": "athlete",
  "атлетический": "athletic",
  "атлетичный": "athletic",
  "атмосфера": "atmosphere",
  "атмосферно": "atmospherically",
  "атмосферность": "atmospheric quality",
  "атмосферный": "atmospheric",
  "атолл": "atoll",
  "атом": "atom",
  "атомный": "atomic",
  "аттракцион": "attraction",
  "аттракторы": "attractors",
  "аттракционы": "attractions",
  "аттракция": "attraction",
  "атрибут": "attribute",
  "атрибутивный": "attributive",
  "атрибутика": "attributes",
  "атрибуция": "attribution",
  "атриум": "atrium",
  "атрофированный": "atrophied",
  "атрофия": "atrophy",
  "атташе": "attaché",
  "аттестат": "certificate",
  "аттестация": "certification",
  "аттитюд": "attitude",
  "аттический": "Attic",
  "аудио": "audio",
  "аудиозапись": "audio recording",
  "аудиокнига": "audiobook",
  "аудиенция": "audience",
  "аудирование": "listening",
  "аудит": "audit",
  "аудитор": "auditor",
  "аудитория": "audience",
  "аукцион": "auction",
  "аул": "village",
  "аура": "aura",
  "аут": "out",
  "аутентификация": "authentication",
  "аутентично": "authentically",
  "аутентичность": "authenticity",
  "аутентичный": "authentic",
  "аутизм": "autism",
  "аутист": "autist",
  "аутодафе": "auto-da-fé",
  "аутсайдер": "outsider",
  "аутсорс": "outsource",
  "аутсорсинг": "outsourcing",
  "афера": "scam",
  "аферист": "swindler",
  "аферистка": "female swindler",
  "афина": "Athena ",
  "афиша": "poster",
  "афоризм": "aphorism",
  "афористичный": "aphoristic",
  "африка": "Africa",
  "африканский": "african",
  "афроамериканец": "African American",
  "афродизиак": "aphrodisiac",
  "афродита": "Aphrodite ",
  "афронт": "affront",
  "аффект": "affect",
  "аффектация": "affectation",
  "аффективный": "affective",
  "афферентный": "afferent",
  "аффикс": "affix",
  "аффинаж": "refining",
  "ахиллесова пята": "Achilles' heel",
  "ахинея": "nonsense",
  "ахнуть": "gasp",
  "ахтунг": "achtung",
  "аэродром": "aerodrome",
  "аэрозоль": "aerosol",
  "аэроплан": "airplane",
  "аэропорт": "airport",
  "аэростат": "airship",
  "азот": "nitrogen"
}
